portpy_photon/__init__.py
portpy_photon/beam.py
portpy_photon/clinical_criteria.py
portpy_photon/cvxpy_prob.py
portpy_photon/cvxpy_prob_old.py
portpy_photon/cvxpy_prob_rev2.py
portpy_photon/evaluation.py
portpy_photon/influence_matrix.py
portpy_photon/optimization.py
portpy_photon/plan.py
portpy_photon/structures.py
portpy_photon/visualization.py
portpy_photon/utils/__init__.py
portpy_photon/utils/load_data.py
portpy_photon/utils/load_metadata.py
portpy_photon/utils/save_nrrd.py
portpy_photon/utils/save_or_load_pickle.py
portpy_photon/utils/slicer_script.py
portpy_photon/utils/sol_change_inf_matrix.py
portpy_photon/utils/view_in_slicer_jupyter.py
portpy_photon-0.0.5.dist-info/LICENSE.txt
portpy_photon-0.0.5.dist-info/METADATA
portpy_photon-0.0.5.dist-info/WHEEL
portpy_photon-0.0.5.dist-info/top_level.txt
portpy_photon-0.0.5.dist-info/RECORD
