Metadata-Version: 2.1
Name: portpy-photon
Version: 0.0.5
Summary: First open-source radiation treatment planning system in Python
Home-page: https://github.com/PortPy-Project/PortPy-Photon
Author: Gourav Jhanwar, Mojtaba Tefagh, Vicki Taasti, Seppo Tuomaala, Saad Nadeem, Masoud Zarepisheh
Author-email: jhanwarg@mskcc.struct, mtefagh@acm.struct, vicki.taasti@maastro.nl, tuomaals@mskcc.struct, nadeems@mskcc.struct, zarepism@mskcc.struct
License: Apache License, Version 2.0
Platform: UNKNOWN
Classifier: Development Status :: 1 - Planning
Classifier: Intended Audience :: Developers
Classifier: Intended Audience :: Education
Classifier: Intended Audience :: Science/Research
Classifier: License :: OSI Approved :: Apache Software License
Classifier: Programming Language :: Python :: 3.7
Classifier: Topic :: Scientific/Engineering :: Mathematics
Classifier: Topic :: Software Development :: Libraries :: Python Modules
Classifier: Topic :: Software Development :: Libraries
Requires-Python: >=3.7
Requires-Dist: cvxpy (>=1.1.18)
Requires-Dist: ecos (>=2.0.10)
Requires-Dist: h5py (>=3.6.0)
Requires-Dist: Mosek (>=9.3.14)
Requires-Dist: natsort (>=8.1.0)
Requires-Dist: numpy (>=1.15)
Requires-Dist: osqp (>=0.4.1)
Requires-Dist: pandas (>=1.1.5)
Requires-Dist: python-dateutil (>=2.8.2)
Requires-Dist: pytz (>=2022.1)
Requires-Dist: qdldl (>=0.1.5)
Requires-Dist: scipy (>=1.5.4)
Requires-Dist: scs (>=3.2.0)
Requires-Dist: six (>=1.16.0)
Requires-Dist: matplotlib (>=3.5.3)
Requires-Dist: Shapely (>=1.8.4)
Requires-Dist: SimpleITK (>=2.0.2)
Requires-Dist: tabulate (>=0.9.0)
Requires-Dist: typing (>=3.7.4.3)
Requires-Dist: jinja2 (>=3.0.1)
Requires-Dist: typing-extensions (>=3.10.0.0)
Requires-Dist: scikit-image (>=0.17.2)
Requires-Dist: patchify (>=0.2.3)
